setup.py
mcptbr/__init__.py
mcptbr/minecraft.py
mcptbr.egg-info/PKG-INFO
mcptbr.egg-info/SOURCES.txt
mcptbr.egg-info/dependency_links.txt
mcptbr.egg-info/requires.txt
mcptbr.egg-info/top_level.txt