Metadata-Version: 2.1
Name: mcptbr
Version: 0.2.6
Summary: Biblioteca para manipular o Minecraft através do python.
Author: Lucas Pereira
Author-email: lucasthe2@gmail.com
License: MIT
